topsis_calculator_abhai/__main__.py
topsis_calculator_abhai/topsis.py
topsis_calculator_abhai-2.1.0.dist-info/METADATA
topsis_calculator_abhai-2.1.0.dist-info/WHEEL
topsis_calculator_abhai-2.1.0.dist-info/entry_points.txt
topsis_calculator_abhai-2.1.0.dist-info/top_level.txt
topsis_calculator_abhai-2.1.0.dist-info/RECORD
